pymbc.py
pymbc-1.1.4.dist-info/LICENSE
pymbc-1.1.4.dist-info/METADATA
pymbc-1.1.4.dist-info/WHEEL
pymbc-1.1.4.dist-info/top_level.txt
pymbc-1.1.4.dist-info/RECORD
