Metadata-Version: 2.1
Name: pymbc
Version: 1.1.4
Summary: A python package for working with MB Century downhole data.
Home-page: https://github.com/tricky67/pymbc
Author: Richard Williams
Author-email: rwilliams@mbcentury.com
Keywords: dab,csv,pts,htcc,Century Logger
Classifier: Development Status :: 4 - Beta
Classifier: Programming Language :: Python :: 3.11
Classifier: Programming Language :: Python :: 3.12
Classifier: Programming Language :: Python :: 3.13
Classifier: Framework :: Matplotlib
Classifier: Environment :: No Input/Output (Daemon)
Classifier: License :: OSI Approved :: GNU General Public License v3 (GPLv3)
Classifier: Intended Audience :: Developers
Classifier: Intended Audience :: Other Audience
Classifier: Intended Audience :: Science/Research
Classifier: Topic :: Text Processing
Classifier: Topic :: Scientific/Engineering
Classifier: Operating System :: Microsoft :: Windows
Classifier: Operating System :: OS Independent
Requires-Python: >=3.11
License-File: LICENSE
Requires-Dist: numpy >=1.24
Requires-Dist: pandas >=1.5
Requires-Dist: matplotlib >=3.6
Requires-Dist: scipy >=1.13.0
